MANIFEST.in
README.rst
setup.py
GitBanshee.egg-info/PKG-INFO
GitBanshee.egg-info/SOURCES.txt
GitBanshee.egg-info/dependency_links.txt
GitBanshee.egg-info/requires.txt
GitBanshee.egg-info/top_level.txt
bin/git-banshee
gitbanshee/__init__.py
gitbanshee/__init__.pyc
gitbanshee/index.html
gitbanshee/server.py
gitbanshee/server.pyc
gitbanshee/utils.py
gitbanshee/utils.pyc
gitbanshee/hooks/post-checkout
gitbanshee/hooks/post-commit
gitbanshee/hooks/post-merge
gitbanshee/static/WebSocketMain.swf
gitbanshee/static/js/howler.min.js
gitbanshee/static/js/socket.io.js
gitbanshee/static/sounds/applause.mp3
gitbanshee/static/sounds/mortal-kombat.mp3