Metadata-Version: 1.1
Name: GitBanshee
Version: 0.1
Summary: Play sound effects when you commit, checkout and merge in git.
Home-page: http://dirtymonkey.co.uk/Git-Banshee
Author: Matt Deacalion Stevens
Author-email: matt@dirtymonkey.co.uk
License: MIT
Keywords: git hooks sound effects
Platform: UNKNOWN
Classifier: Development Status :: 4 - Beta
Classifier: Environment :: Console
Classifier: Environment :: Web Environment
Classifier: Environment :: Other Environment
Classifier: Intended Audience :: Developers
Classifier: License :: OSI Approved :: MIT License
Classifier: Natural Language :: English
Classifier: Operating System :: Unix
Classifier: Programming Language :: Python :: 2.6
Classifier: Programming Language :: Python :: 2.7
Classifier: Topic :: Games/Entertainment
Classifier: Topic :: Multimedia :: Sound/Audio
Classifier: Topic :: Software Development
Classifier: Topic :: Software Development :: User Interfaces
